bess/__init__.py
bess/_cbess.cp35-win_amd64.pyd
bess/cbess.py
bess/gen_data.py
bess/linear.py
bess-0.0.12.dist-info/LICENSE
bess-0.0.12.dist-info/METADATA
bess-0.0.12.dist-info/WHEEL
bess-0.0.12.dist-info/top_level.txt
bess-0.0.12.dist-info/RECORD
