Metadata-Version: 2.1
Name: bess
Version: 0.0.12
Summary: bess Python Package
Home-page: https://github.com/Mamba413/bess
Author: Kangkang Jiang, Jin Zhu, Yanhang Zhang, Shijie Quan, Xueqin Wang
Author-email: jiangkk3@mail2.sysu.edu.cn
Maintainer: Kangkang Jiang
Maintainer-email: jiangkk3@mail2.sysu.edu.cn
License: GPL-3
Platform: UNKNOWN
Classifier: Programming Language :: Python
Classifier: Programming Language :: Python :: 3.5
Classifier: Programming Language :: Python :: 3.6
Classifier: Programming Language :: Python :: 3.7
Classifier: Programming Language :: Python :: 3.8
Requires-Python: >=3.5
Requires-Dist: numpy
